llama_index/embeddings/gemini/__init__.py
llama_index/embeddings/gemini/base.py
llama_index_embeddings_gemini-0.3.2.dist-info/LICENSE
llama_index_embeddings_gemini-0.3.2.dist-info/METADATA
llama_index_embeddings_gemini-0.3.2.dist-info/WHEEL
llama_index_embeddings_gemini-0.3.2.dist-info/RECORD
